{"rules": [{"id": "rule_001", "category": "time_based", "description": "Turn on bedroom lights at 7:00 AM", "conditions_logic": "AND", "conditions": [{"type": "environment", "parameter": "is_daytime", "operator": "==", "value": true}], "actions": [{"device_id": "lights_bedroom", "command": "turn_on", "parameters": {}}]}, {"id": "rule_002", "category": "weather", "description": "If the temperature is above 28\u00b0C, turn on the living room AC", "conditions_logic": "AND", "conditions": [{"type": "environment", "parameter": "temperature", "operator": ">", "value": 28}], "actions": [{"device_id": "ac_living_room", "command": "turn_on", "parameters": {}}]}]}